file_type_classifier/__init__.py
file_type_classifier/main.py
file_type_classifier-0.1.1.dist-info/LICENSE
file_type_classifier-0.1.1.dist-info/WHEEL
file_type_classifier-0.1.1.dist-info/METADATA
file_type_classifier-0.1.1.dist-info/RECORD
