Metadata-Version: 2.1
Name: file-type-classifier
Version: 0.1.1
Summary: 
Author: lipe14-ops
Author-email: filipe.ns1001@gmai.com
Requires-Python: >=3.10,<4.0
Classifier: Programming Language :: Python :: 3
Classifier: Programming Language :: Python :: 3.10
Classifier: Programming Language :: Python :: 3.11
